[{"source":"public/brilliantexport/problems/../problems/05/05.html","category":"Calculus","level":3,"title":"0.5! ......","body":"{\"type\":\"doc\",\"content\":[{\"type\":\"paragraph\",\"content\":[{\"type\":\"text\",\"text\":\"What is the value of \"},{\"type\":\"katex\",\"content\":[{\"type\":\"text\",\"text\":\"\\\\left(\\\\frac 12\\\\right)!\"}],\"attrs\":{\"inline\":true}},{\"type\":\"text\",\"text\":\"? \"}]},{\"type\":\"text\",\"text\":\"\\n\\n\"},{\"type\":\"paragraph\",\"content\":[{\"type\":\"katex\",\"content\":[{\"type\":\"text\",\"text\":\"\"}],\"attrs\":{\"inline\":true}}]},{\"type\":\"text\",\"text\":\"\\n\\n\"},{\"type\":\"paragraph\",\"content\":[{\"type\":\"text\",\"text\":\"Notation:\",\"marks\":[{\"type\":\"bold\"}]},{\"type\":\"text\",\"text\":\" \"},{\"type\":\"katex\",\"content\":[{\"type\":\"text\",\"text\":\"!\"}],\"attrs\":{\"inline\":true}},{\"type\":\"text\",\"text\":\" denotes the \"},{\"type\":\"text\",\"text\":\"factorial notation\",\"marks\":[{\"attrs\":{\"href\":\"\",\"target\":\"_blank\"},\"type\":\"link\"}]},{\"type\":\"text\",\"text\":\". For example \"},{\"type\":\"katex\",\"content\":[{\"type\":\"text\",\"text\":\"8!=1\\\\times 2\\\\times 3 \\\\times 4 \\\\times 5 \\\\times 6 \\\\times 7 \\\\times 8\"}],\"attrs\":{\"inline\":true}},{\"type\":\"text\",\"text\":\".\"}]}]}","answers":[{"correct":false,"text":"{\"type\":\"doc\",\"content\":[{\"type\":\"text\",\"text\":\"\\n\\n\\nnot possible\\n\\n\"}]}"},{"correct":true,"text":"{\"type\":\"doc\",\"content\":[{\"type\":\"text\",\"text\":\"\\n\\n\\n0.886227..\\n\\n\"}]}"},{"correct":false,"text":"{\"type\":\"doc\",\"content\":[{\"type\":\"text\",\"text\":\"\\n\\n\\ninfinite\\n\\n\"}]}"},{"correct":false,"text":"{\"type\":\"doc\",\"content\":[{\"type\":\"text\",\"text\":\"\\n\\n\\n0.234971..\\n\\n\"}]}"}],"author":{"profile":"https://brilliant.org/profile/suresh-uugof0/","name":"suresh jh","age":17,"location":"India"},"discussion":[{"author":{"avatar":"../../brioche/avatars-2/resized/45/01cc373802bc9078310429a4135c7b4c.cdc07d6ce4-Xkwf56Tq4X.jpg?width=45","profile":"https://brilliant.org/profile/chew-seong-872sn7/","name":"Chew-Seong Cheong"},"date":"Feb. 11, 2018, 4:07 a.m.","body":"{\"type\":\"doc\",\"content\":[{\"type\":\"text\",\"text\":\"\\n                                \\n                                \\n                                \\n                                    \\n                                        \"},{\"type\":\"paragraph\",\"content\":[{\"type\":\"text\",\"text\":\"The \"},{\"type\":\"text\",\"text\":\"gamma function\",\"marks\":[{\"attrs\":{\"href\":\"\",\"target\":\"_blank\"},\"type\":\"link\"}]},{\"type\":\"text\",\"text\":\" serves as an extension of the factorial function beyond the non-negative integer. And one of the functional equations is \"},{\"type\":\"katex\",\"content\":[{\"type\":\"text\",\"text\":\"\\\\Gamma (s) = (s-1)!\"}],\"attrs\":{\"inline\":true}},{\"type\":\"text\",\"text\":\". Therefore, \"}]},{\"type\":\"text\",\"text\":\"\\n\\n\"},{\"type\":\"paragraph\",\"content\":[{\"type\":\"katex\",\"content\":[{\"type\":\"text\",\"text\":\"\\\\begin{aligned} \\\\left(\\\\frac 12\\\\right) ! & = \\\\Gamma \\\\left(\\\\frac 32\\\\right) & \\\\small \\\\color{#3D99F6} \\\\text{Using the identity: }\\\\Gamma (s+1) = s\\\\Gamma (s)\\n\\\\\\\\ & = \\\\frac 12 \\\\Gamma \\\\left(\\\\frac 12\\\\right) & \\\\small \\\\color{#3D99F6} \\\\text{Note that }\\\\Gamma \\\\left(\\\\frac 12\\\\right) = \\\\sqrt \\\\pi\\n\\\\\\\\ & = \\\\frac {\\\\sqrt \\\\pi}2\\n\\\\\\\\ & = \\\\boxed{0.8862269...} \\\\end{aligned} \"}],\"attrs\":{\"inline\":true}}]},{\"type\":\"text\",\"text\":\"\\n\\n                                    \\n                                \\n                            \"}]}","reactions":[5,2,0,0],"comments":[{"id":"295189","level":0,"replies":[{"id":"295197","level":1,"replies":[],"author":{"profile":"https://brilliant.org/profile/chew-seong-872sn7/","name":"Chew-Seong Cheong"},"date":"- 3 years, 3 months ago","body":"{\"type\":\"doc\",\"content\":[{\"type\":\"text\",\"text\":\"\\n                                        \\n\\n                                        \"},{\"type\":\"paragraph\",\"content\":[{\"type\":\"text\",\"text\":\"\\n                                            \\n\\n                                            \\n                                            Not that I know of. Gamma function was devised by Euler to extent the discreet factorial to the continuous. In my opinion one of the greatest contribution by Euler.\\n\\n                                        \"}]},{\"type\":\"text\",\"text\":\"\\n\\n                                        \\n                                            \\n                                        \\n\\n                                        \\n\\n                                        \\n    \\n\\n    \\n\\n\\n                                    \"}]}"}],"author":{"profile":"https://brilliant.org/profile/louis-jlke3x/","name":"Louis Ullman"},"date":"- 3 years, 3 months ago","body":"{\"type\":\"doc\",\"content\":[{\"type\":\"text\",\"text\":\"\\n                                        \\n\\n                                        \"},{\"type\":\"paragraph\",\"content\":[{\"type\":\"text\",\"text\":\"\\n                                            \\n\\n                                            \\n                                            Would there be a way to estimate the answer without using the gamma function?\\n\\n                                        \"}]},{\"type\":\"text\",\"text\":\"\\n\\n                                        \\n                                            \\n                                        \\n\\n                                        \\n\\n                                        \\n    \\n\\n    \\n\\n\\n                                    \"}]}"}]},{"author":{"avatar":"../../brioche/avatars-2/resized/45/6edede9d58d847fa452c76d437c0a56c.514a7ebb74-VT0Pn7sgD7.jpg?width=45","profile":"https://brilliant.org/profile/bernard-l9psuh/","name":"Bernard Peh"},"date":"Feb. 12, 2018, 4:58 a.m.","body":"{\"type\":\"doc\",\"content\":[{\"type\":\"text\",\"text\":\"\\n                                \\n                                \\n                                \\n                                    \\n                                        \"},{\"type\":\"paragraph\",\"content\":[{\"type\":\"text\",\"text\":\"Factorials are actually only defined for integers more than or equal to \"},{\"type\":\"katex\",\"content\":[{\"type\":\"text\",\"text\":\"0\"}],\"attrs\":{\"inline\":true}},{\"type\":\"text\",\"text\":\" so technically it should be \\\"not possible\\\",but , \"},{\"type\":\"text\",\"text\":\"the gamma function\",\"marks\":[{\"attrs\":{\"href\":\"\",\"target\":\"_blank\"},\"type\":\"link\"}]},{\"type\":\"text\",\"text\":\" which is the \\\"extension\\\" to factorials yields \"},{\"type\":\"katex\",\"content\":[{\"type\":\"text\",\"text\":\"\\\\displaystyle \\\\frac{\\\\sqrt{\\\\pi}}{2}\"}],\"attrs\":{\"inline\":true}},{\"type\":\"text\",\"text\":\". A little bit misleading though!\"}]},{\"type\":\"text\",\"text\":\"\\n\\n                                    \\n                                \\n                            \"}]}","reactions":[0,0,0,0],"comments":[]},{"author":{"avatar":"../../site_media/images/default-avatar-globe.png","profile":"https://brilliant.org/profile/suresh-uugof0/","name":"Suresh Jh"},"date":"Feb. 9, 2018, 8:51 a.m.","body":"{\"type\":\"doc\",\"content\":[{\"type\":\"text\",\"text\":\"\\n                                \\n                                \\n                                \\n                                    \\n                                        \"},{\"type\":\"paragraph\",\"content\":[{\"type\":\"image\",\"attrs\":{\"src\":\"/brilliantexport/brioche/uploads/LHTj9NH98S-img_20180209_221524.png?width=1200\"}},{\"type\":\"text\",\"text\":\"\\nwe know, Γ(n+1) = n Γ(n)\"}]},{\"type\":\"text\",\"text\":\"\\n\\n\"},{\"type\":\"paragraph\",\"content\":[{\"type\":\"text\",\"text\":\"if n = 1/2\"}]},{\"type\":\"text\",\"text\":\"\\n\\n\"},{\"type\":\"paragraph\",\"content\":[{\"type\":\"text\",\"text\":\"Γ(3/2) = Γ(1/2)/2\"}]},{\"type\":\"text\",\"text\":\"\\n\\n\"},{\"type\":\"paragraph\",\"content\":[{\"type\":\"text\",\"text\":\"=> Γ(3/2) = √π/2\"}]},{\"type\":\"text\",\"text\":\"\\n\\n\"},{\"type\":\"paragraph\",\"content\":[{\"type\":\"text\",\"text\":\"=> (1/2)! = √π/2\"}]},{\"type\":\"text\",\"text\":\"\\n\\n                                    \\n                                \\n                            \"}]}","reactions":[0,0,0,0],"comments":[]},{"author":{"avatar":"../../brioche/avatars-2/resized/45/5e4e9fd02501a254ef43b594481cefee.9c9b1ffae8-p38LcQUIwH.jpg?width=45","profile":"https://brilliant.org/profile/digvijay-o0arto/","name":"Digvijay Singh"},"date":"Feb. 9, 2018, 8:48 a.m.","body":"{\"type\":\"doc\",\"content\":[{\"type\":\"text\",\"text\":\"\\n                                \\n                                \\n                                \\n                                    \\n                                        \"},{\"type\":\"paragraph\",\"content\":[{\"type\":\"text\",\"text\":\"cliché..\"}]},{\"type\":\"text\",\"text\":\"\\n\\n\"},{\"type\":\"paragraph\",\"content\":[{\"type\":\"katex\",\"content\":[{\"type\":\"text\",\"text\":\"\\\\begin{aligned}\\n& \\\\left(\\\\dfrac{1}{2}\\\\right)! \\\\\\\\\\n= & \\\\Pi\\\\left(\\\\dfrac{1}{2}\\\\right) \\\\\\\\\\n= & \\\\displaystyle \\\\int_{0}^{\\\\infty} t^{1/2}e^{-t} dt \\\\\\\\\\n= & \\\\dfrac{\\\\sqrt{\\\\pi}}{2} \\\\\\\\\\n\\\\approx & \\\\boxed{0.8862269...} \\\\\\\\\\n\\\\end{aligned}\"}],\"attrs\":{\"inline\":true}}]},{\"type\":\"text\",\"text\":\"\\n\\n                                    \\n                                \\n                            \"}]}","reactions":[0,0,0,0],"comments":[]}]},{"source":"public/brilliantexport/problems/../problems/09-1/09-1.html","category":"Algebra","level":1,"title":"0.9 = 1","body":"{\"type\":\"doc\",\"content\":[{\"type\":\"paragraph\",\"content\":[{\"type\":\"text\",\"text\":\"0.9999999 (keeps on going for ever, recurring) is equal to 1.\"}]}]}","answers":[{"correct":true,"text":"{\"type\":\"doc\",\"content\":[{\"type\":\"text\",\"text\":\"\\n\\n\\nTrue\\n\\n\"}]}"},{"correct":false,"text":"{\"type\":\"doc\",\"content\":[{\"type\":\"text\",\"text\":\"\\n\\n\\nFalse\\n\\n\"}]}"}],"author":{"profile":"https://brilliant.org/profile/etienne-unur8m/","name":"Etienne **","age":15,"location":"United Kingdom"},"discussion":[{"author":{"avatar":"../../site_media/images/default-avatar-globe.png","profile":"https://brilliant.org/profile/a-former-brilliant-Yy8tDA/","name":"A Former Brilliant Member"},"date":"Nov. 13, 2018, 11:18 p.m.","body":"{\"type\":\"doc\",\"content\":[{\"type\":\"text\",\"text\":\"\\n                                \\n                                \\n                                \\n                                    \\n                                        \"},{\"type\":\"paragraph\",\"content\":[{\"type\":\"katex\",\"content\":[{\"type\":\"text\",\"text\":\"\\\\dfrac {1}{9} = 0.11111.........\"}],\"attrs\":{\"inline\":true}}]},{\"type\":\"text\",\"text\":\"\\n\\n\"},{\"type\":\"paragraph\",\"content\":[{\"type\":\"katex\",\"content\":[{\"type\":\"text\",\"text\":\"1 =9\\\\times (0.11111......) = 0.9999.......\"}],\"attrs\":{\"inline\":true}}]},{\"type\":\"text\",\"text\":\"\\n\\n\"},{\"type\":\"paragraph\",\"content\":[{\"type\":\"text\",\"text\":\"Hence,          \"},{\"type\":\"katex\",\"content\":[{\"type\":\"text\",\"text\":\"0.9999.......=1\"}],\"attrs\":{\"inline\":true}}]},{\"type\":\"text\",\"text\":\"\\n\\n\"},{\"type\":\"paragraph\",\"content\":[{\"type\":\"katex\",\"content\":[{\"type\":\"text\",\"text\":\"ANSWER:\\\\boxed {TRUE}\"}],\"attrs\":{\"inline\":true}}]},{\"type\":\"text\",\"text\":\"\\n\\n                                    \\n                                \\n                            \"}]}","reactions":[3,0,0,0],"comments":[]},{"author":{"avatar":"../../brioche/avatars-2/resized/45/1e999e30723b96fc394007ddb4c4785b.1e999e30723b96fc394007ddb4c4785b.jpg?width=45","profile":"https://brilliant.org/profile/parth-v60cs5/","name":"Parth Sankhe"},"date":"Nov. 13, 2018, 10:42 p.m.","body":"{\"type\":\"doc\",\"content\":[{\"type\":\"text\",\"text\":\"\\n                                \\n                                \\n                                \\n                                    \\n                                        \"},{\"type\":\"paragraph\",\"content\":[{\"type\":\"text\",\"text\":\"If \"},{\"type\":\"katex\",\"content\":[{\"type\":\"text\",\"text\":\"x=0.9999...\"}],\"attrs\":{\"inline\":true}},{\"type\":\"text\",\"text\":\",\"}]},{\"type\":\"text\",\"text\":\"\\n\\n\"},{\"type\":\"paragraph\",\"content\":[{\"type\":\"katex\",\"content\":[{\"type\":\"text\",\"text\":\"10x=9.9999...\"}],\"attrs\":{\"inline\":true}}]},{\"type\":\"text\",\"text\":\"\\n\\n\"},{\"type\":\"paragraph\",\"content\":[{\"type\":\"text\",\"text\":\"Subtracting the two equations, \"},{\"type\":\"katex\",\"content\":[{\"type\":\"text\",\"text\":\"9x=9\"}],\"attrs\":{\"inline\":true}},{\"type\":\"text\",\"text\":\", \"},{\"type\":\"katex\",\"content\":[{\"type\":\"text\",\"text\":\"x=1\"}],\"attrs\":{\"inline\":true}}]},{\"type\":\"text\",\"text\":\"\\n\\n                                    \\n                                \\n                            \"}]}","reactions":[2,0,0,0],"comments":[]},{"author":{"avatar":"../../site_media/images/default-avatar-globe.png","profile":"https://brilliant.org/profile/etienne-unur8m/","name":"Etienne **"},"date":"Nov. 13, 2018, 1:51 p.m.","body":"{\"type\":\"doc\",\"content\":[{\"type\":\"text\",\"text\":\"\\n                                \\n                                \\n                                \\n                                    \\n                                        \"},{\"type\":\"paragraph\",\"content\":[{\"type\":\"text\",\"text\":\"1 ÷ 3 = 0.333 (recurring). 0.333 (recurring) x 3 = 1 or 0.999 (recurring). Can be proved other ways too.\"}]},{\"type\":\"text\",\"text\":\"\\n\\n                                    \\n                                \\n                            \"}]}","reactions":[2,0,0,0],"comments":[]},{"author":{"avatar":"../../brioche/avatars-2/resized/45/ddf8955a27fe4a74b713d23f19079608.ddf8955a27fe4a74b713d23f19079608.jpg?width=45","profile":"https://brilliant.org/profile/jordan-0vmn1a/","name":"Jordan Cahn"},"date":"Nov. 14, 2018, 10:15 a.m.","body":"{\"type\":\"doc\",\"content\":[{\"type\":\"text\",\"text\":\"\\n                                \\n                                \\n                                \\n                                    \\n                                        \"},{\"type\":\"paragraph\",\"content\":[{\"type\":\"katex\",\"content\":[{\"type\":\"text\",\"text\":\"\\\\begin{aligned}\\n0.999\\\\ldots &= \\\\frac{9}{10} + \\\\frac{9}{100} + \\\\cdots \\\\\\\\\\n&= \\\\sum_{i=1}^\\\\infty \\\\frac{9}{10^i} \\\\\\\\\\n&= \\\\frac{9}{10}\\\\sum_{i=0}^\\\\infty \\\\frac{1}{10^i} && \\\\color{#3D99F6}\\\\text{The sum converges since }-1<\\\\frac{1}{10}<1 \\\\\\\\\\n&= \\\\frac{9}{10} \\\\times \\\\frac{1}{1-\\\\frac{1}{10}} \\\\\\\\\\n&= \\\\frac{9}{10} \\\\times \\\\frac{10}{9} = \\\\boxed{1}\\n\\\\end{aligned}\"}],\"attrs\":{\"inline\":false}},{\"type\":\"text\",\"text\":\" \"}]},{\"type\":\"text\",\"text\":\"\\n\\n\"},{\"type\":\"horizontalRule\"},{\"type\":\"text\",\"text\":\"\\n\\n\"},{\"type\":\"paragraph\",\"content\":[{\"type\":\"katex\",\"content\":[{\"type\":\"text\",\"text\":\"\\\\begin{aligned}\\n0.999\\\\ldots &= \\\\lim_{n\\\\to\\\\infty} \\\\frac{\\\\overbrace{99\\\\cdots9}^{n\\\\text{ }9\\\\text{s}}}{1\\\\underbrace{00\\\\cdots0}_{n\\\\text{ }0\\\\text{s}}} \\\\\\\\\\n&= \\\\lim_{n\\\\to\\\\infty} \\\\frac{10^n-1}{10^n} \\\\\\\\\\n&= \\\\lim_{n\\\\to\\\\infty} \\\\left(1-\\\\frac{1}{10^n}\\\\right) && \\\\color{#3D99F6} \\\\lim_{n\\\\to\\\\infty}\\\\frac{1}{10^n} = 0 \\\\\\\\\\n&= 1 - 0 = \\\\boxed{1}\\n\\\\end{aligned}\"}],\"attrs\":{\"inline\":false}}]},{\"type\":\"text\",\"text\":\"\\n\\n                                    \\n                                \\n                            \"}]}","reactions":[1,0,0,0],"comments":[]}]},{"source":"public/brilliantexport/problems/../problems/0999/0999.html","category":"Calculus","level":1,"title":"0.999..0.999..0.999..","body":"{\"type\":\"doc\",\"content\":[{\"type\":\"paragraph\",\"content\":[{\"type\":\"text\",\"text\":\"Solve:\"}]},{\"type\":\"text\",\"text\":\"\\n\\n\"},{\"type\":\"paragraph\",\"content\":[{\"type\":\"katex\",\"content\":[{\"type\":\"text\",\"text\":\"\\\\displaystyle\\\\sum _{ n=1 }^{ \\\\infty  }{ \\\\frac { 9 }{ { 10 }^{ n } }  } \"}],\"attrs\":{\"inline\":true}}]}]}","answers":[{"correct":true,"text":"1"}],"author":{"profile":"https://brilliant.org/profile/victor-cvujb3/","name":"Victor Paes Plinio","age":21,"location":"Brazil"},"discussion":[{"author":{"avatar":"../../brioche/avatars-2/resized/45/ff94c14f240f75719b586487ec750ab7.79eed281eb2b50c828720b6b1216ad33_1.jpg?width=45","profile":"https://brilliant.org/profile/raymond-john-04dusw/","name":"Raymond John Diaz"},"date":"July 23, 2014, 4:16 a.m.","body":"{\"type\":\"doc\",\"content\":[{\"type\":\"text\",\"text\":\"\\n                                \\n                                \\n                                \\n                                    \\n                                        \"},{\"type\":\"paragraph\",\"content\":[{\"type\":\"text\",\"text\":\"Well it's just an Infinite Geometric Progression\"}]},{\"type\":\"text\",\"text\":\"\\n\\n\"},{\"type\":\"paragraph\",\"content\":[{\"type\":\"text\",\"text\":\"a_1 = 9/10\"}]},{\"type\":\"text\",\"text\":\"\\n\\n\"},{\"type\":\"paragraph\",\"content\":[{\"type\":\"text\",\"text\":\"common ratio of 1/10\"}]},{\"type\":\"text\",\"text\":\"\\n\\n\"},{\"type\":\"paragraph\",\"content\":[{\"type\":\"text\",\"text\":\"S= a_1 / 1-r\"}]},{\"type\":\"text\",\"text\":\"\\n\\n\"},{\"type\":\"paragraph\",\"content\":[{\"type\":\"text\",\"text\":\"S= (9/10) / [1-(1/10)]\"}]},{\"type\":\"text\",\"text\":\"\\n\\n\"},{\"type\":\"paragraph\",\"content\":[{\"type\":\"text\",\"text\":\"S= (9/10) / [9/10]\"}]},{\"type\":\"text\",\"text\":\"\\n\\n\"},{\"type\":\"paragraph\",\"content\":[{\"type\":\"text\",\"text\":\"S=1\"}]},{\"type\":\"text\",\"text\":\"\\n\\n                                    \\n                                \\n                            \"}]}","reactions":[1,0,0,0],"comments":[]}]}]